keycdn/__init__.py
keycdn/keycdn.py
keycdn-0.4.3.dist-info/METADATA
keycdn-0.4.3.dist-info/WHEEL
keycdn-0.4.3.dist-info/top_level.txt
keycdn-0.4.3.dist-info/RECORD
