Metadata-Version: 2.1
Name: keycdn
Version: 0.4.3
Summary: A Python REST Client for KeyCDN API
Home-page: https://github.com/keycdn/python-keycdn-api
Author: KeyCDN
License: UNKNOWN
Keywords: cdn,content delivery network,keycdn
Platform: UNKNOWN
Classifier: Programming Language :: Python :: 2.7
Classifier: Programming Language :: Python :: 3
Requires-Dist: requests (>=2.11.1)
